setup.py
datastore/__init__.py
datastore.mongo.egg-info/PKG-INFO
datastore.mongo.egg-info/SOURCES.txt
datastore.mongo.egg-info/dependency_links.txt
datastore.mongo.egg-info/namespace_packages.txt
datastore.mongo.egg-info/requires.txt
datastore.mongo.egg-info/top_level.txt
datastore/mongo/__init__.py
datastore/mongo/test.py