Metadata-Version: 1.0
Name: datastore.mongo
Version: 0.1.1
Summary: mongodb datastore implementation
Home-page: http://github.com/datastore/datastore.mongo
Author: Juan Batiz-Benet
Author-email: juan@benet.ai
License: MIT License
Keywords: datastore,mongodb
Platform: UNKNOWN
Classifier: Topic :: Database
Classifier: Topic :: Database :: Front-Ends
